[
    {
        "name":"albertt itzep",
        "gender":"M",
        "username":"pedrito123",
        "email":"alaberttitzep123@gmail.com",
        "password":"sistemas@123"
    },
    {
        "name":"Nataly Guzman",
        "gender":"F",
        "username":"nata123",
        "email":"alaberttitzep123@gmail.com",
        "password":"sistemas@123"
    },
    {
        "name":"Samuel itzep",
        "gender":"M",
        "username":"samuel1233",
        "email":"alaberttitzep123@gmail.com",
        "password":"sistemas@123"
    },
    {
        "name":"marlon mayen",
        "gender":"M",
        "username":"Marlor123",
        "email":"alaberttitzep123@gmail.com",
        "password":"sistemas@123"
    },
    {
        "name":"Paty Raymundo",
        "gender":"F",
        "username":"Paty123",
        "email":"alaberttitzep123@gmail.com",
        "password":"sistemas@123"
    },
    {
        "name":"Maynor Itzep",
        "gender":"M",
        "username":"Maynor123",
        "email":"alaberttitzep123@gmail.com",
        "password":"sistemas@123"
    },
    {
        "name":"Betzabe Itzep",
        "gender":"M",
        "username":"Betza123",
        "email":"alaberttitzep123@gmail.com",
        "password":"sistemas@123"
    },
    {
        "name":"Mariana Mayen",
        "gender":"F",
        "username":"mariana123",
        "email":"alaberttitzep123@gmail.com",
        "password":"sistemas@123"
    },
    {
        "name":"Lesly Mayen",
        "gender":"M",
        "username":"Lesly123",
        "email":"alaberttitzep123@gmail.com",
        "password":"sistemas@123"
    },
    {
        "name":"Marleny Lopez",
        "gender":"M",
        "username":"Marleny123",
        "email":"alaberttitzep123@gmail.com",
        "password":"sistemas@123"
    }
]